datacontract_specification/__init__.py
datacontract_specification/model.py
datacontract_specification/py.typed
datacontract_specification/schema.json
datacontract_specification-1.2.2.dist-info/METADATA
datacontract_specification-1.2.2.dist-info/WHEEL
datacontract_specification-1.2.2.dist-info/licenses/LICENSE
datacontract_specification-1.2.2.dist-info/RECORD
